px4_log_tool/__init__.py
px4_log_tool/cli.py
px4_log_tool/msg_reference.csv
px4_log_tool/runners.py
px4_log_tool/processing_modules/__init__.py
px4_log_tool/processing_modules/converter.py
px4_log_tool/processing_modules/merger.py
px4_log_tool/processing_modules/metagen.py
px4_log_tool/processing_modules/resampler.py
px4_log_tool/util/__init__.py
px4_log_tool/util/components.py
px4_log_tool/util/logger.py
px4_log_tool/util/tui.py
px4_log_tool-0.6.3.dist-info/METADATA
px4_log_tool-0.6.3.dist-info/WHEEL
px4_log_tool-0.6.3.dist-info/entry_points.txt
px4_log_tool-0.6.3.dist-info/top_level.txt
px4_log_tool-0.6.3.dist-info/RECORD
